[{"firstName":"Adelice","lastName":"Lingley","year":1987,"movie":"Presentation, or Charlotte and Her Steak (Présentation ou Charlotte et son steak)","alive":false},
{"firstName":"Kendall","lastName":"Mayger","year":1993,"movie":"Three on a Weekend","alive":true},
{"firstName":"Felicle","lastName":"Merigeau","year":1985,"movie":"Bad Company","alive":true},
{"firstName":"Julianna","lastName":"Fawckner","year":2012,"movie":"They Live by Night","alive":false},
{"firstName":"Ezra","lastName":"Brafferton","year":2010,"movie":"Entertaining Angels: The Dorothy Day Story","alive":true},
{"firstName":"Odelle","lastName":"Lawden","year":2007,"movie":"Spice World","alive":false},
{"firstName":"Thorsten","lastName":"Waddell","year":1994,"movie":"Mighty Joe Young","alive":false},
{"firstName":"Julio","lastName":"Adshede","year":1994,"movie":"Big Street, The","alive":true},
{"firstName":"Carmon","lastName":"Ellor","year":2011,"movie":"Tall Story","alive":true},
{"firstName":"Galen","lastName":"Abdee","year":1990,"movie":"Looking for Maria Sanchez","alive":true},
{"firstName":"Danila","lastName":"Widdecombe","year":2006,"movie":"Cat Run 2","alive":false},
{"firstName":"Fair","lastName":"Buxcy","year":1993,"movie":"Great Waltz, The","alive":false},
{"firstName":"Eadmund","lastName":"Ranfield","year":2003,"movie":"Captain America: The First Avenger","alive":false},
{"firstName":"Mikel","lastName":"Goldingay","year":2001,"movie":"X2: X-Men United","alive":false},
{"firstName":"Gaylor","lastName":"Revans","year":2009,"movie":"Feet First","alive":true},
{"firstName":"Jerome","lastName":"Lezemore","year":2000,"movie":"Mr. Hobbs Takes a Vacation","alive":false},
{"firstName":"Jarrid","lastName":"Lippini","year":2012,"movie":"Cecil B. DeMented","alive":true},
{"firstName":"Benji","lastName":"Clutterham","year":2001,"movie":"Monte Walsh","alive":false},
{"firstName":"Doroteya","lastName":"Dahlberg","year":2002,"movie":"Cobb","alive":false},
{"firstName":"Corella","lastName":"Grzelewski","year":2010,"movie":"Sinivalkoinen valhe","alive":false},
{"firstName":"Vern","lastName":"Boddie","year":1984,"movie":"Prince of Tides, The","alive":true},
{"firstName":"Clara","lastName":"Barrows","year":2003,"movie":"Estomago: A Gastronomic Story","alive":false},
{"firstName":"Aubrie","lastName":"Rodbourne","year":1992,"movie":"Dead End","alive":false},
{"firstName":"Englebert","lastName":"Edlyn","year":2008,"movie":"Daddy Long Legs","alive":true},
{"firstName":"Westleigh","lastName":"Kleinhausen","year":1994,"movie":"Generation Kill","alive":false},
{"firstName":"Gayel","lastName":"Broadhurst","year":1994,"movie":"Mr. Average","alive":false},
{"firstName":"Kit","lastName":"MacMeanma","year":2004,"movie":"Sleeping Beauty, The (La belle endormie)","alive":false},
{"firstName":"Arleen","lastName":"Iiannone","year":2007,"movie":"Eyes Wide Open (Einayim Petukhoth)","alive":true},
{"firstName":"Gigi","lastName":"Kampshell","year":1993,"movie":"Dinner at Eight","alive":false},
{"firstName":"Devora","lastName":"Novelli","year":2010,"movie":"Black Moon Rising","alive":false}]